WavveParser.py
WavveParser-0.1.dist-info/METADATA
WavveParser-0.1.dist-info/WHEEL
WavveParser-0.1.dist-info/top_level.txt
WavveParser-0.1.dist-info/RECORD
