Metadata-Version: 2.1
Name: WavveParser
Version: 0.1
Summary: wavve parser
Home-page: https://github.com/CATERINA-SEUL/WavveParser
Author: caterina
Author-email: dalgona91@gmail.com
License: MIT
Download-URL: https://github.com/CATERINA-SEUL/WavveParser/archive/WavveParser-0.1.tar.gz
Keywords: wavve
Platform: UNKNOWN
Classifier: Programming Language :: Python :: 3
Classifier: Programming Language :: Python :: 3.2
Classifier: Programming Language :: Python :: 3.3
Classifier: Programming Language :: Python :: 3.4
Classifier: Programming Language :: Python :: 3.5
Classifier: Programming Language :: Python :: 3.6
Classifier: Programming Language :: Python :: 3.7
Classifier: License :: OSI Approved :: MIT License
Requires-Python: >=3
